serve.py
insertoknameAuthlibFork/__init__.py
insertoknameAuthlibFork/consts.py
insertoknameAuthlibFork/deprecate.py
insertoknameAuthlibFork/common/__init__.py
insertoknameAuthlibFork/common/encoding.py
insertoknameAuthlibFork/common/errors.py
insertoknameAuthlibFork/common/security.py
insertoknameAuthlibFork/common/urls.py
insertoknameAuthlibFork/integrations/__init__.py
insertoknameAuthlibFork/integrations/base_client/__init__.py
insertoknameAuthlibFork/integrations/base_client/async_app.py
insertoknameAuthlibFork/integrations/base_client/async_openid.py
insertoknameAuthlibFork/integrations/base_client/errors.py
insertoknameAuthlibFork/integrations/base_client/framework_integration.py
insertoknameAuthlibFork/integrations/base_client/registry.py
insertoknameAuthlibFork/integrations/base_client/sync_app.py
insertoknameAuthlibFork/integrations/base_client/sync_openid.py
insertoknameAuthlibFork/integrations/django_client/__init__.py
insertoknameAuthlibFork/integrations/django_client/apps.py
insertoknameAuthlibFork/integrations/django_client/integration.py
insertoknameAuthlibFork/integrations/django_oauth1/__init__.py
insertoknameAuthlibFork/integrations/django_oauth1/authorization_server.py
insertoknameAuthlibFork/integrations/django_oauth1/nonce.py
insertoknameAuthlibFork/integrations/django_oauth1/resource_protector.py
insertoknameAuthlibFork/integrations/django_oauth2/__init__.py
insertoknameAuthlibFork/integrations/django_oauth2/authorization_server.py
insertoknameAuthlibFork/integrations/django_oauth2/endpoints.py
insertoknameAuthlibFork/integrations/django_oauth2/requests.py
insertoknameAuthlibFork/integrations/django_oauth2/resource_protector.py
insertoknameAuthlibFork/integrations/django_oauth2/signals.py
insertoknameAuthlibFork/integrations/flask_client/__init__.py
insertoknameAuthlibFork/integrations/flask_client/apps.py
insertoknameAuthlibFork/integrations/flask_client/integration.py
insertoknameAuthlibFork/integrations/flask_oauth1/__init__.py
insertoknameAuthlibFork-0.0.0.dist-info/METADATA
insertoknameAuthlibFork-0.0.0.dist-info/WHEEL
insertoknameAuthlibFork-0.0.0.dist-info/top_level.txt
insertoknameAuthlibFork-0.0.0.dist-info/RECORD
