Metadata-Version: 2.1
Name: insertoknameAuthlibFork
Version: 0.0.0
Summary: The ultimate Python library in building OAuth and OpenID Connect servers and clients.
Author-email: Hsiaoming Yang <me@lepture.com>
License: BSD-3-Clause
Requires-Python: >=3.8
Requires-Dist: cryptography
